sardinecake/__init__.py
sardinecake/__main__.py
sardinecake/_version.py
sardinecake/auth.py
sardinecake/clone.py
sardinecake/defaults.py
sardinecake/domain.py
sardinecake/exportvm.py
sardinecake/gitlab_executor.py
sardinecake/gziparchive.py
sardinecake/importvm.py
sardinecake/logger.py
sardinecake/namespace.py
sardinecake/ociregistry.py
sardinecake/qcow.py
sardinecake/ssh.py
sardinecake/utils.py
sardinecake/virsh.py
sardinecake/schema/sardineconfig.schema.json
sardinecake-0.4.2.dist-info/licenses/LICENSE.md
sardinecake-0.4.2.dist-info/METADATA
sardinecake-0.4.2.dist-info/WHEEL
sardinecake-0.4.2.dist-info/entry_points.txt
sardinecake-0.4.2.dist-info/top_level.txt
sardinecake-0.4.2.dist-info/RECORD
