Metadata-Version: 2.4
Name: sardinecake
Version: 0.4.2
Summary: Manage libvirt VMs via OCI.
Author-email: IOhannes m zmölnig <zmoelnig@iem.at>
License-Expression: AGPL-3.0-or-later
Project-URL: Homepage, https://git.iem.at/devtools/sardinecake
Project-URL: Documentation, https://sardinecake.readthedocs.io/
Project-URL: Repository, https://git.iem.at/devtools/sardinecake.git
Project-URL: Issues, https://git.iem.at/devtools/sardinecake/-/issues
Requires-Python: >=3.8
License-File: LICENSE.md
Requires-Dist: libvirt-python>=10
Requires-Dist: jsonschema>=4
Requires-Dist: python-magic>=0.4
Requires-Dist: paramiko>=3
Dynamic: license-file
